ndn_hydra/__init__.py
ndn_hydra/client/__init__.py
ndn_hydra/client/main.py
ndn_hydra/client/functions/__init__.py
ndn_hydra/client/functions/delete.py
ndn_hydra/client/functions/fetch.py
ndn_hydra/client/functions/insert.py
ndn_hydra/client/functions/query.py
ndn_hydra/repo/__init__.py
ndn_hydra/repo/config.yaml
ndn_hydra/repo/group_messages/__init__.py
ndn_hydra/repo/group_messages/add.py
ndn_hydra/repo/group_messages/claim.py
ndn_hydra/repo/group_messages/heartbeat.py
ndn_hydra/repo/group_messages/message.py
ndn_hydra/repo/group_messages/remove.py
ndn_hydra/repo/group_messages/specific_message.py
ndn_hydra/repo/group_messages/store.py
ndn_hydra/repo/group_messages/update.py
ndn_hydra/repo/handles/__init__.py
ndn_hydra/repo/handles/delete_command_handle.py
ndn_hydra/repo/handles/insert_command_handle.py
ndn_hydra/repo/handles/protocol_handle_base.py
ndn_hydra/repo/handles/query_handle.py
ndn_hydra/repo/handles/read_handle.py
ndn_hydra/repo/main/__init__.py
ndn_hydra/repo/main/main.py
ndn_hydra/repo/main/main_loop.py
ndn_hydra/repo/modules/__init__.py
ndn_hydra/repo/modules/command_table.py
ndn_hydra/repo/modules/data_storage.py
ndn_hydra/repo/modules/favor_calculator.py
ndn_hydra/repo/modules/file_fetcher.py
ndn_hydra/repo/modules/file_remover.py
ndn_hydra/repo/modules/global_view.py
ndn_hydra/repo/modules/heartbeat_tracker.py
ndn_hydra/repo/modules/read_config.py
ndn_hydra/repo/modules/read_remaining_space.py
ndn_hydra/repo/protocol/__init__.py
ndn_hydra/repo/protocol/base_models.py
ndn_hydra/repo/protocol/status_code.py
ndn_hydra/repo/protocol/tlv.py
ndn_hydra/repo/utils/__init__.py
ndn_hydra/repo/utils/concurrent_fetcher.py
ndn_hydra/repo/utils/garbage_collector.py
ndn_hydra/repo/utils/pubsub.py
ndn_hydra_repo-1.0.0.dist-info/AUTHORS.rst
ndn_hydra_repo-1.0.0.dist-info/LICENSE.rst
ndn_hydra_repo-1.0.0.dist-info/METADATA
ndn_hydra_repo-1.0.0.dist-info/WHEEL
ndn_hydra_repo-1.0.0.dist-info/entry_points.txt
ndn_hydra_repo-1.0.0.dist-info/top_level.txt
ndn_hydra_repo-1.0.0.dist-info/RECORD
